README.rst
setup.py
osbrain/__init__.py
osbrain/address.py
osbrain/agent.py
osbrain/common.py
osbrain/helper.py
osbrain/logging.py
osbrain/nameserver.py
osbrain/proxy.py
osbrain.egg-info/PKG-INFO
osbrain.egg-info/SOURCES.txt
osbrain.egg-info/dependency_links.txt
osbrain.egg-info/requires.txt
osbrain.egg-info/top_level.txt