Metadata-Version: 2.1
Name: osbrain
Version: 0.6.4
Summary: A general-purpose multi-agent-system module
Home-page: https://github.com/opensistemas-hub/osbrain
Author: Miguel Sánchez de León Peque
Author-email: msdeleon@opensistemas.com
License: Apache License, Version 2.0
Keywords: osbrain multi-agent system
Platform: UNKNOWN
Classifier: Development Status :: 3 - Alpha
Classifier: Intended Audience :: Developers
Classifier: Intended Audience :: Science/Research
Classifier: Topic :: Software Development :: Build Tools
Classifier: License :: OSI Approved :: Apache Software License
Classifier: Programming Language :: Python :: 3
Classifier: Programming Language :: Python :: 3.5
Classifier: Programming Language :: Python :: 3.6
Classifier: Programming Language :: Python :: 3.7
Classifier: Programming Language :: Python :: Implementation :: CPython
Provides-Extra: dev
